non_admin_draftail/__init__.py
non_admin_draftail/apps.py
non_admin_draftail/conf.py
non_admin_draftail/forms.py
non_admin_draftail/static/non_admin_draftail/draftail.css
non_admin_draftail/static/non_admin_draftail/draftail.css.map
non_admin_draftail/static/non_admin_draftail/modal-workflow.js
non_admin_draftail/static_src/.gitignore
non_admin_draftail/static_src/README.md
non_admin_draftail/static_src/package-lock.json
non_admin_draftail/static_src/package.json
non_admin_draftail/static_src/src/index.scss
non_admin_draftail/static_src/src/styles/chooser.scss
non_admin_draftail/static_src/src/styles/editor.scss
non_admin_draftail/static_src/src/styles/modal.scss
non_admin_draftail/static_src/src/styles/tooltip.scss
non_admin_draftail/templates/non_admin_draftail/_draftail_css.html
non_admin_draftail/templates/non_admin_draftail/_draftail_js.html
non_admin_draftail/templates/non_admin_draftail/document/upload.html
non_admin_draftail/templates/non_admin_draftail/draftail_media.html
non_admin_draftail/templates/non_admin_draftail/embed/chooser.html
non_admin_draftail/templates/non_admin_draftail/image/select_format.html
non_admin_draftail/templates/non_admin_draftail/image/upload.html
non_admin_draftail/templates/non_admin_draftail/link/_link_types.html
non_admin_draftail/templates/non_admin_draftail/link/anchor_link.html
non_admin_draftail/templates/non_admin_draftail/link/email_link.html
non_admin_draftail/templates/non_admin_draftail/link/external_link.html
non_admin_draftail/templates/non_admin_draftail/link/phone_link.html
non_admin_draftail/templates/non_admin_draftail/modal_base.html
non_admin_draftail/templates/non_admin_draftail/widgets/non_admin_draftail_rich_text_area.html
non_admin_draftail/templatetags/__init__.py
non_admin_draftail/templatetags/non_admin_draftail_tags.py
non_admin_draftail/urls.py
non_admin_draftail/views/__init__.py
non_admin_draftail/views/document.py
non_admin_draftail/views/embed.py
non_admin_draftail/views/image.py
non_admin_draftail-0.17.2.dist-info/LICENSE
non_admin_draftail-0.17.2.dist-info/METADATA
non_admin_draftail-0.17.2.dist-info/WHEEL
non_admin_draftail-0.17.2.dist-info/RECORD
