Metadata-Version: 2.1
Name: non-admin-draftail
Version: 0.17.2
Summary: You can now use Wagtail Draftail editor on non-admin pages
Home-page: https://timonweb.com
License: MIT
Author: Tim Kamanin
Author-email: tim@timonweb.com
Requires-Python: >=3.7,<4.0
Classifier: License :: OSI Approved :: MIT License
Classifier: Programming Language :: Python :: 3
Classifier: Programming Language :: Python :: 3.7
Classifier: Programming Language :: Python :: 3.8
Classifier: Programming Language :: Python :: 3.9
Classifier: Programming Language :: Python :: 3.10
Classifier: Programming Language :: Python :: 3.11
Requires-Dist: wagtail (>=4.1)
Project-URL: Repository, https://github.com/timonweb/non-admin-draftail
